<?xml version="1.0" encoding="utf-8" standalone="yes"?>
<Gesture Name = "X">
	<Stroke>
		<Point X = "103,2" Y = "-178" T = "0" Pressure = "0" />
		<Point X = "100" Y = "-165,2" T = "0" Pressure = "0" />
		<Point X = "96,80001" Y = "-151,6" T = "0" Pressure = "0" />
		<Point X = "93,60001" Y = "-141,2" T = "0" Pressure = "0" />
		<Point X = "93,60001" Y = "-141,2" T = "0" Pressure = "0" />
		<Point X = "90,40001" Y = "-131,6" T = "0" Pressure = "0" />
		<Point X = "85,60001" Y = "-124,4" T = "0" Pressure = "0" />
		<Point X = "80,00001" Y = "-118,8" T = "0" Pressure = "0" />
		<Point X = "80,00001" Y = "-118,8" T = "0" Pressure = "0" />
		<Point X = "74,40001" Y = "-117,2" T = "0" Pressure = "0" />
		<Point X = "68,80001" Y = "-116,4" T = "0" Pressure = "0" />
		<Point X = "68,80001" Y = "-116,4" T = "0" Pressure = "0" />
	</Stroke>
	<Stroke>
		<Point X = "67,20001" Y = "-172,4" T = "0" Pressure = "0" />
		<Point X = "72,80001" Y = "-165,2" T = "0" Pressure = "0" />
		<Point X = "72,80001" Y = "-165,2" T = "0" Pressure = "0" />
		<Point X = "80,00001" Y = "-156,4" T = "0" Pressure = "0" />
		<Point X = "86,40001" Y = "-147,6" T = "0" Pressure = "0" />
		<Point X = "86,40001" Y = "-147,6" T = "0" Pressure = "0" />
		<Point X = "92,80001" Y = "-140,4" T = "0" Pressure = "0" />
		<Point X = "99,20001" Y = "-131,6" T = "0" Pressure = "0" />
		<Point X = "99,20001" Y = "-131,6" T = "0" Pressure = "0" />
		<Point X = "104,8" Y = "-124,4" T = "0" Pressure = "0" />
		<Point X = "111,2" Y = "-118" T = "0" Pressure = "0" />
		<Point X = "118,4" Y = "-111,6" T = "0" Pressure = "0" />
		<Point X = "124,8" Y = "-106" T = "0" Pressure = "0" />
		<Point X = "124,8" Y = "-106" T = "0" Pressure = "0" />
		<Point X = "129,6" Y = "-103,6" T = "0" Pressure = "0" />
		<Point X = "129,6" Y = "-103,6" T = "0" Pressure = "0" />
		<Point X = "133,6" Y = "-102" T = "0" Pressure = "0" />
	</Stroke>
</Gesture>
